Classfile /Users/fidel/github/Test/src/main/java/design_pattern/singleton/EnumSingleton.class
  Last modified 2021-7-14; size 1224 bytes
  MD5 checksum 7d1b4100d3ddfa6c96a9cd144a3f95bb
  Compiled from "EnumSingleton.java"
public final class design_pattern.singleton.enumsingleton.EnumSingleton extends java.lang.Enum<design_pattern.singleton.enumsingleton.EnumSingleton>
  minor version: 0
  major version: 52
  flags: ACC_PUBLIC, ACC_FINAL, ACC_SUPER, ACC_ENUM
Constant pool:
   #1 = Fieldref           #4.#37         // design_pattern/singleton/EnumSingleton.$VALUES:[Ldesign_pattern/singleton/EnumSingleton;
   #2 = Methodref          #38.#39        // "[Ldesign_pattern/singleton/EnumSingleton;".clone:()Ljava/lang/Object;
   #3 = Class              #17            // "[Ldesign_pattern/singleton/EnumSingleton;"
   #4 = Class              #40            // design_pattern/singleton/EnumSingleton
   #5 = Methodref          #13.#41        // java/lang/Enum.valueOf:(Ljava/lang/Class;Ljava/lang/String;)Ljava/lang/Enum;
   #6 = Methodref          #13.#42        // java/lang/Enum."<init>":(Ljava/lang/String;I)V
   #7 = Fieldref           #43.#44        // java/lang/System.out:Ljava/io/PrintStream;
   #8 = Methodref          #4.#45         // design_pattern/singleton/EnumSingleton.hashCode:()I
   #9 = Methodref          #46.#47        // java/io/PrintStream.println:(I)V
  #10 = String             #14            // INSTANCE
  #11 = Methodref          #4.#42         // design_pattern/singleton/EnumSingleton."<init>":(Ljava/lang/String;I)V
  #12 = Fieldref           #4.#48         // design_pattern/singleton/EnumSingleton.INSTANCE:Ldesign_pattern/singleton/EnumSingleton;
  #13 = Class              #49            // java/lang/Enum
  #14 = Utf8               INSTANCE
  #15 = Utf8               Ldesign_pattern/singleton/EnumSingleton;
  #16 = Utf8               $VALUES
  #17 = Utf8               [Ldesign_pattern/singleton/EnumSingleton;
  #18 = Utf8               values
  #19 = Utf8               ()[Ldesign_pattern/singleton/EnumSingleton;
  #20 = Utf8               Code
  #21 = Utf8               LineNumberTable
  #22 = Utf8               valueOf
  #23 = Utf8               (Ljava/lang/String;)Ldesign_pattern/singleton/EnumSingleton;
  #24 = Utf8               LocalVariableTable
  #25 = Utf8               name
  #26 = Utf8               Ljava/lang/String;
  #27 = Utf8               <init>
  #28 = Utf8               (Ljava/lang/String;I)V
  #29 = Utf8               this
  #30 = Utf8               Signature
  #31 = Utf8               ()V
  #32 = Utf8               print
  #33 = Utf8               <clinit>
  #34 = Utf8               Ljava/lang/Enum<Ldesign_pattern/singleton/EnumSingleton;>;
  #35 = Utf8               SourceFile
  #36 = Utf8               EnumSingleton.java
  #37 = NameAndType        #16:#17        // $VALUES:[Ldesign_pattern/singleton/EnumSingleton;
  #38 = Class              #17            // "[Ldesign_pattern/singleton/EnumSingleton;"
  #39 = NameAndType        #50:#51        // clone:()Ljava/lang/Object;
  #40 = Utf8               design_pattern/singleton/EnumSingleton
  #41 = NameAndType        #22:#52        // valueOf:(Ljava/lang/Class;Ljava/lang/String;)Ljava/lang/Enum;
  #42 = NameAndType        #27:#28        // "<init>":(Ljava/lang/String;I)V
  #43 = Class              #53            // java/lang/System
  #44 = NameAndType        #54:#55        // out:Ljava/io/PrintStream;
  #45 = NameAndType        #56:#57        // hashCode:()I
  #46 = Class              #58            // java/io/PrintStream
  #47 = NameAndType        #59:#60        // println:(I)V
  #48 = NameAndType        #14:#15        // INSTANCE:Ldesign_pattern/singleton/EnumSingleton;
  #49 = Utf8               java/lang/Enum
  #50 = Utf8               clone
  #51 = Utf8               ()Ljava/lang/Object;
  #52 = Utf8               (Ljava/lang/Class;Ljava/lang/String;)Ljava/lang/Enum;
  #53 = Utf8               java/lang/System
  #54 = Utf8               out
  #55 = Utf8               Ljava/io/PrintStream;
  #56 = Utf8               hashCode
  #57 = Utf8               ()I
  #58 = Utf8               java/io/PrintStream
  #59 = Utf8               println
  #60 = Utf8               (I)V
{
  public static final design_pattern.singleton.enumsingleton.EnumSingleton INSTANCE;
    descriptor: Ldesign_pattern/singleton/EnumSingleton;
    flags: ACC_PUBLIC, ACC_STATIC, ACC_FINAL, ACC_ENUM

  private static final design_pattern.singleton.enumsingleton.EnumSingleton[] $VALUES;
    descriptor: [Ldesign_pattern/singleton/EnumSingleton;
    flags: ACC_PRIVATE, ACC_STATIC, ACC_FINAL, ACC_SYNTHETIC

  public static design_pattern.singleton.enumsingleton.EnumSingleton[] values();
    descriptor: ()[Ldesign_pattern/singleton/EnumSingleton;
    flags: ACC_PUBLIC, ACC_STATIC
    Code:
      stack=1, locals=0, args_size=0
         0: getstatic     #1                  // Field $VALUES:[Ldesign_pattern/singleton/EnumSingleton;
         3: invokevirtual #2                  // Method "[Ldesign_pattern/singleton/EnumSingleton;".clone:()Ljava/lang/Object;
         6: checkcast     #3                  // class "[Ldesign_pattern/singleton/EnumSingleton;"
         9: areturn
      LineNumberTable:
        line 12: 0

  public static design_pattern.singleton.enumsingleton.EnumSingleton valueOf(java.lang.String);
    descriptor: (Ljava/lang/String;)Ldesign_pattern/singleton/EnumSingleton;
    flags: ACC_PUBLIC, ACC_STATIC
    Code:
      stack=2, locals=1, args_size=1
         0: ldc           #4                  // class design_pattern/singleton/EnumSingleton
         2: aload_0
         3: invokestatic  #5                  // Method java/lang/Enum.valueOf:(Ljava/lang/Class;Ljava/lang/String;)Ljava/lang/Enum;
         6: checkcast     #4                  // class design_pattern/singleton/EnumSingleton
         9: areturn
      LineNumberTable:
        line 12: 0
      LocalVariableTable:
        Start  Length  Slot  Name   Signature
            0      10     0  name   Ljava/lang/String;

  private design_pattern.singleton.enumsingleton.EnumSingleton();
    descriptor: (Ljava/lang/String;I)V
    flags: ACC_PRIVATE
    Code:
      stack=3, locals=3, args_size=3
         0: aload_0
         1: aload_1
         2: iload_2
         3: invokespecial #6                  // Method java/lang/Enum."<init>":(Ljava/lang/String;I)V
         6: return
      LineNumberTable:
        line 18: 0
        line 20: 6
      LocalVariableTable:
        Start  Length  Slot  Name   Signature
            0       7     0  this   Ldesign_pattern/singleton/EnumSingleton;
    Signature: #31                          // ()V

  public void print();
    descriptor: ()V
    flags: ACC_PUBLIC
    Code:
      stack=2, locals=1, args_size=1
         0: getstatic     #7                  // Field java/lang/System.out:Ljava/io/PrintStream;
         3: aload_0
         4: invokevirtual #8                  // Method hashCode:()I
         7: invokevirtual #9                  // Method java/io/PrintStream.println:(I)V
        10: return
      LineNumberTable:
        line 23: 0
        line 24: 10
      LocalVariableTable:
        Start  Length  Slot  Name   Signature
            0      11     0  this   Ldesign_pattern/singleton/EnumSingleton;

  static {};
    descriptor: ()V
    flags: ACC_STATIC
    Code:
      stack=4, locals=0, args_size=0
         0: new           #4                  // class design_pattern/singleton/EnumSingleton
         3: dup
         4: ldc           #10                 // String INSTANCE
         6: iconst_0
         7: invokespecial #11                 // Method "<init>":(Ljava/lang/String;I)V
        10: putstatic     #12                 // Field INSTANCE:Ldesign_pattern/singleton/EnumSingleton;
        13: iconst_1
        14: anewarray     #4                  // class design_pattern/singleton/EnumSingleton
        17: dup
        18: iconst_0
        19: getstatic     #12                 // Field INSTANCE:Ldesign_pattern/singleton/EnumSingleton;
        22: aastore
        23: putstatic     #1                  // Field $VALUES:[Ldesign_pattern/singleton/EnumSingleton;
        26: return
      LineNumberTable:
        line 14: 0
        line 12: 13
}
Signature: #34                          // Ljava/lang/Enum<Ldesign_pattern/singleton/EnumSingleton;>;
SourceFile: "EnumSingleton.java"
